ultrastarparser/__init__.py
ultrastarparser/audio.py
ultrastarparser/io.py
ultrastarparser/library.py
ultrastarparser/song.py
ultrastarparser/transform_funcs.py
ultrastarparser/versions.py
ultrastarparser-0.6.14.dist-info/LICENCE
ultrastarparser-0.6.14.dist-info/METADATA
ultrastarparser-0.6.14.dist-info/WHEEL
ultrastarparser-0.6.14.dist-info/RECORD
