Metadata-Version: 2.3
Name: ultrastarParser
Version: 0.6.14
Summary: Parser for Ultrastar text files.
License: MIT
Keywords: ultrastar,parser,karaoke
Author: randompersona1
Author-email: 74961116+randompersona1@users.noreply.github.com
Requires-Python: >=3.10,<4.0
Classifier: License :: OSI Approved :: MIT License
Classifier: Programming Language :: Python :: 3
Classifier: Programming Language :: Python :: 3.10
Classifier: Programming Language :: Python :: 3.11
Classifier: Programming Language :: Python :: 3.12
Classifier: Programming Language :: Python :: 3.13
Requires-Dist: requests (>=2.32.3,<3.0.0)
Requires-Dist: tinytag (>=1.10.1,<2.0.0)
Project-URL: Homepage, https://github.com/randompersona1/ultrastarParser
